setup.cfg
setup.py
waveletspec/__init__.py
waveletspec/check_fit.py
waveletspec/clean_spectra.py
waveletspec/coadd_spectra.py
waveletspec/interpolate_grid.py
waveletspec/load_spectra.py
waveletspec/normalise_spectra.py
waveletspec/plot_spectra.py
waveletspec/resample.py
waveletspec/wavelet_analysis.py
waveletspec/wavelet_analysis_plot.py
waveletspec/write_spectra.py
waveletspec.egg-info/PKG-INFO
waveletspec.egg-info/SOURCES.txt
waveletspec.egg-info/dependency_links.txt
waveletspec.egg-info/top_level.txt