Metadata-Version: 1.1
Name: waveletspec
Version: 1.3
Summary: Wavelet analysis of echelle spectra
Home-page: https://github.com/samgill844/waveletspec
Author: Samuel Gill
Author-email: s.gill@keele.ac.uk
License: MIT License
